passwordgeneratorpy/__init__.py
passwordgeneratorpy/__main__.py
passwordgeneratorpy/passwordgeneratorpy.py
passwordgeneratorpy-0.1.dist-info/LICENCE
passwordgeneratorpy-0.1.dist-info/METADATA
passwordgeneratorpy-0.1.dist-info/WHEEL
passwordgeneratorpy-0.1.dist-info/entry_points.txt
passwordgeneratorpy-0.1.dist-info/top_level.txt
passwordgeneratorpy-0.1.dist-info/RECORD
